<annotation>
	<folder>0028</folder>
	<filename>0028-00000018.jpg</filename>
	<path>/home/vanejessi/Etiquetado de imagenes/smart-traffic-sensor-lab/vehicles-dataset/not-labeled-images/0028/0028-00000018.jpg</path>
	<source>
		<database>Unknown</database>
	</source>
	<size>
		<width>520</width>
		<height>520</height>
		<depth>3</depth>
	</size>
	<segmented>0</segmented>
	<object>
		<name>car</name>
		<pose>Unspecified</pose>
		<truncated>0</truncated>
		<difficult>0</difficult>
		<bndbox>
			<xmin>342</xmin>
			<ymin>301</ymin>
			<xmax>402</xmax>
			<ymax>375</ymax>
		</bndbox>
	</object>
	<object>
		<name>car</name>
		<pose>Unspecified</pose>
		<truncated>0</truncated>
		<difficult>0</difficult>
		<bndbox>
			<xmin>178</xmin>
			<ymin>140</ymin>
			<xmax>204</xmax>
			<ymax>166</ymax>
		</bndbox>
	</object>
	<object>
		<name>bus</name>
		<pose>Unspecified</pose>
		<truncated>0</truncated>
		<difficult>0</difficult>
		<bndbox>
			<xmin>254</xmin>
			<ymin>42</ymin>
			<xmax>281</xmax>
			<ymax>77</ymax>
		</bndbox>
	</object>
	<object>
		<name>car</name>
		<pose>Unspecified</pose>
		<truncated>0</truncated>
		<difficult>0</difficult>
		<bndbox>
			<xmin>201</xmin>
			<ymin>75</ymin>
			<xmax>218</xmax>
			<ymax>95</ymax>
		</bndbox>
	</object>
	<object>
		<name>car</name>
		<pose>Unspecified</pose>
		<truncated>0</truncated>
		<difficult>0</difficult>
		<bndbox>
			<xmin>225</xmin>
			<ymin>72</ymin>
			<xmax>238</xmax>
			<ymax>87</ymax>
		</bndbox>
	</object>
	<object>
		<name>car</name>
		<pose>Unspecified</pose>
		<truncated>0</truncated>
		<difficult>0</difficult>
		<bndbox>
			<xmin>223</xmin>
			<ymin>57</ymin>
			<xmax>235</xmax>
			<ymax>69</ymax>
		</bndbox>
	</object>
</annotation>
