<annotation>
	<folder>0117</folder>
	<filename>0117-00000039.jpg</filename>
	<path>/home/vanejessi/vehicle dataset/Dataset/GRAM-RTMv4/images/0117/0117-00000039.jpg</path>
	<source>
		<database>Unknown</database>
	</source>
	<size>
		<width>800</width>
		<height>480</height>
		<depth>3</depth>
	</size>
	<segmented>0</segmented>
	<object>
		<name>car</name>
		<pose>Unspecified</pose>
		<truncated>0</truncated>
		<difficult>0</difficult>
		<bndbox>
			<xmin>480</xmin>
			<ymin>80</ymin>
			<xmax>502</xmax>
			<ymax>96</ymax>
		</bndbox>
	</object>
	<object>
		<name>van</name>
		<pose>Unspecified</pose>
		<truncated>0</truncated>
		<difficult>0</difficult>
		<bndbox>
			<xmin>438</xmin>
			<ymin>66</ymin>
			<xmax>464</xmax>
			<ymax>90</ymax>
		</bndbox>
	</object>
	<object>
		<name>car</name>
		<pose>Unspecified</pose>
		<truncated>0</truncated>
		<difficult>0</difficult>
		<bndbox>
			<xmin>396</xmin>
			<ymin>81</ymin>
			<xmax>418</xmax>
			<ymax>97</ymax>
		</bndbox>
	</object>
	<object>
		<name>car</name>
		<pose>Unspecified</pose>
		<truncated>0</truncated>
		<difficult>0</difficult>
		<bndbox>
			<xmin>360</xmin>
			<ymin>78</ymin>
			<xmax>379</xmax>
			<ymax>94</ymax>
		</bndbox>
	</object>
	<object>
		<name>car</name>
		<pose>Unspecified</pose>
		<truncated>0</truncated>
		<difficult>0</difficult>
		<bndbox>
			<xmin>426</xmin>
			<ymin>96</ymin>
			<xmax>456</xmax>
			<ymax>117</ymax>
		</bndbox>
	</object>
	<object>
		<name>car</name>
		<pose>Unspecified</pose>
		<truncated>0</truncated>
		<difficult>0</difficult>
		<bndbox>
			<xmin>210</xmin>
			<ymin>331</ymin>
			<xmax>320</xmax>
			<ymax>423</ymax>
		</bndbox>
	</object>
</annotation>
