<annotation>
	<folder>0082</folder>
	<filename>0082-00000113.jpg</filename>
	<path>/home/redo/workspaces/jderobot/smart-traffic-sensor-lab/vehicles-dataset/not-labeled-images/0082/0082-00000113.jpg</path>
	<source>
		<database>Unknown</database>
	</source>
	<size>
		<width>520</width>
		<height>520</height>
		<depth>3</depth>
	</size>
	<segmented>0</segmented>
	<object>
		<name>car</name>
		<pose>Unspecified</pose>
		<truncated>0</truncated>
		<difficult>0</difficult>
		<bndbox>
			<xmin>314</xmin>
			<ymin>134</ymin>
			<xmax>344</xmax>
			<ymax>169</ymax>
		</bndbox>
	</object>
	<object>
		<name>van</name>
		<pose>Unspecified</pose>
		<truncated>0</truncated>
		<difficult>0</difficult>
		<bndbox>
			<xmin>263</xmin>
			<ymin>50</ymin>
			<xmax>280</xmax>
			<ymax>74</ymax>
		</bndbox>
	</object>
	<object>
		<name>car</name>
		<pose>Unspecified</pose>
		<truncated>0</truncated>
		<difficult>0</difficult>
		<bndbox>
			<xmin>291</xmin>
			<ymin>47</ymin>
			<xmax>305</xmax>
			<ymax>65</ymax>
		</bndbox>
	</object>
</annotation>
