<annotation>
	<folder>0070</folder>
	<filename>0070-00000071.jpg</filename>
	<path>/home/vanejessi/Etiquetado de imagenes/smart-traffic-sensor-lab/vehicles-dataset/not-labeled-images/0070/0070-00000071.jpg</path>
	<source>
		<database>Unknown</database>
	</source>
	<size>
		<width>520</width>
		<height>520</height>
		<depth>3</depth>
	</size>
	<segmented>0</segmented>
	<object>
		<name>car</name>
		<pose>Unspecified</pose>
		<truncated>0</truncated>
		<difficult>0</difficult>
		<bndbox>
			<xmin>273</xmin>
			<ymin>422</ymin>
			<xmax>340</xmax>
			<ymax>519</ymax>
		</bndbox>
	</object>
	<object>
		<name>car</name>
		<pose>Unspecified</pose>
		<truncated>0</truncated>
		<difficult>0</difficult>
		<bndbox>
			<xmin>264</xmin>
			<ymin>133</ymin>
			<xmax>283</xmax>
			<ymax>156</ymax>
		</bndbox>
	</object>
	<object>
		<name>car</name>
		<pose>Unspecified</pose>
		<truncated>0</truncated>
		<difficult>0</difficult>
		<bndbox>
			<xmin>226</xmin>
			<ymin>101</ymin>
			<xmax>243</xmax>
			<ymax>118</ymax>
		</bndbox>
	</object>
	<object>
		<name>car</name>
		<pose>Unspecified</pose>
		<truncated>0</truncated>
		<difficult>0</difficult>
		<bndbox>
			<xmin>258</xmin>
			<ymin>63</ymin>
			<xmax>269</xmax>
			<ymax>76</ymax>
		</bndbox>
	</object>
	<object>
		<name>car</name>
		<pose>Unspecified</pose>
		<truncated>0</truncated>
		<difficult>0</difficult>
		<bndbox>
			<xmin>219</xmin>
			<ymin>57</ymin>
			<xmax>228</xmax>
			<ymax>66</ymax>
		</bndbox>
	</object>
	<object>
		<name>car</name>
		<pose>Unspecified</pose>
		<truncated>0</truncated>
		<difficult>0</difficult>
		<bndbox>
			<xmin>238</xmin>
			<ymin>44</ymin>
			<xmax>245</xmax>
			<ymax>55</ymax>
		</bndbox>
	</object>
</annotation>
